{
  "現在発生中の任務一覧です。": "Daftar misi yang tersedia saat ini.",
  "同時に": "Anda dapat melakukan hingga ",
  "個まで遂行することが可能です。": " misi sehari",
  "南西海域に「基地航空隊」を展開中…": "Mengerahkan \"Skuadron Udara Berbasis Darat\"\nke Wilayah Barat Daya...",
  "中部海域に「基地航空隊」を展開中…": "Mengerahkan \"Skuadron Udara Berbasis Darat\"\nke wilayah tengah...",
  "飛行場設営完了！　中部海域に「基地航空隊」を展開しました！": "Pengaturan lapangan terbang selesai! Kami telah mengerahkan pasukan kami\n\"Skuadron Udara Berbasis Darat\" ke Area Tengah!",
  "飛行場設営完了！　南西海域に「基地航空隊」を展開しました！": "Pengaturan lapangan terbang selesai! Kami telah mengerahkan pasukan kami\n\"Skuadron Udara Berbasis Darat\" ke Wilayah Barat Daya!",
  "第一航空戦隊「Ryuusei Kai」精鋭艦攻隊\n「Ryuusei Kai (Sk. CarDiv...」編成完了！出撃開始！": "Pembentukan Skuadron Udara 1 「Ryuusei Kai」to\nSkuadron Pengebom Torpedo Elit 「Ryuusei Kai (Sk. CarDiv 1)」\nmenyelesaikan! Memulai serangan mendadak!",
  "第2艦隊が": "Armada ke-2",
  "第3艦隊が": "Armada ke-3",
  "第4艦隊が": "Armada ke-4",
  "解放されました！": "telah dibuka kuncinya!",
  "大型艦建造が": "Dermaga Konstruksi Kapal Besar",
  "開放されました！": "telah dibuka kuncinya!",
  "dummy": "forNoComma"
}